cliglue/__init__.py
cliglue/version.py
cliglue/args/__init__.py
cliglue/args/args_que.py
cliglue/args/container.py
cliglue/autocomplete/__init__.py
cliglue/autocomplete/autocomplete.py
cliglue/autocomplete/install.py
cliglue/builder/__init__.py
cliglue/builder/builder.py
cliglue/builder/rule.py
cliglue/builder/rule_factory.py
cliglue/builder/typedef.py
cliglue/completers/__init__.py
cliglue/completers/file.py
cliglue/help/__init__.py
cliglue/help/help.py
cliglue/parser/__init__.py
cliglue/parser/context.py
cliglue/parser/error.py
cliglue/parser/inject.py
cliglue/parser/internal_vars.py
cliglue/parser/keyword.py
cliglue/parser/matcher.py
cliglue/parser/parser.py
cliglue/parser/transform.py
cliglue/parser/validate.py
cliglue/parser/value.py
cliglue/types/__init__.py
cliglue/types/filesystem.py
cliglue/types/time.py
cliglue/utils/__init__.py
cliglue/utils/files.py
cliglue/utils/input.py
cliglue/utils/output.py
cliglue/utils/regex.py
cliglue/utils/shell.py
cliglue/utils/strings.py
cliglue/utils/time.py
tests/__init__.py
tests/asserts.py
tests/args/__init__.py
tests/args/test_args_container.py
tests/args/test_args_que.py
tests/autocomplete/__init__.py
tests/autocomplete/test_autocomplete.py
tests/autocomplete/test_bash_install.py
tests/builder/__init__.py
tests/builder/test_definition_error.py
tests/builder/test_usage.py
tests/builder/test_validate.py
tests/completers/__init__.py
tests/completers/test_file_completer.py
tests/help/__init__.py
tests/help/test_help.py
tests/help/test_version.py
tests/parser/__init__.py
tests/parser/actions.py
tests/parser/test_choices.py
tests/parser/test_default_action.py
tests/parser/test_dictionary.py
tests/parser/test_empty.py
tests/parser/test_flag.py
tests/parser/test_many_arguments.py
tests/parser/test_param.py
tests/parser/test_positional_argument.py
tests/parser/test_primary_option.py
tests/parser/test_subcommand.py
tests/types/__init__.py
tests/types/test_custom_types.py
tests/types/test_filesystem_types.py
cliglue-1.1.3.dist-info/LICENSE
cliglue-1.1.3.dist-info/METADATA
cliglue-1.1.3.dist-info/WHEEL
cliglue-1.1.3.dist-info/top_level.txt
cliglue-1.1.3.dist-info/RECORD
