Metadata-Version: 2.1
Name: cliglue
Version: 1.1.3
Summary: Declarative parser for command line interfaces
Home-page: https://github.com/igrek51/cliglue
Author: igrek51
Author-email: igrek51.dev@gmail.com
License: MIT
Platform: UNKNOWN
Classifier: Programming Language :: Python :: 3
Classifier: License :: OSI Approved :: MIT License
Classifier: Operating System :: OS Independent
Requires-Python: >=3.6.0
Requires-Dist: dataclasses
